ultrapyup/__init__.py
ultrapyup/ai_rules.py
ultrapyup/config/__init__.py
ultrapyup/config/ruff.py
ultrapyup/config/ty.py
ultrapyup/editor/__init__.py
ultrapyup/editor/rule.py
ultrapyup/editor/setting.py
ultrapyup/editor/utils.py
ultrapyup/initialize.py
ultrapyup/layout.py
ultrapyup/migrate.py
ultrapyup/package_manager/__init__.py
ultrapyup/package_manager/pm.py
ultrapyup/package_manager/utils.py
ultrapyup/precommit/__init__.py
ultrapyup/precommit/tool.py
ultrapyup/precommit/utils.py
ultrapyup/resources/.pre-commit-config.yaml
ultrapyup/resources/.ruff_cache/.gitignore
ultrapyup/resources/.ruff_cache/CACHEDIR.TAG
ultrapyup/resources/.vscode/extensions.json
ultrapyup/resources/.vscode/settings.json
ultrapyup/resources/.zed/settings.json
ultrapyup/resources/lefthook.yaml
ultrapyup/resources/ruff.toml
ultrapyup/utils.py
ultrapyup-0.8.0.dist-info/WHEEL
ultrapyup-0.8.0.dist-info/entry_points.txt
ultrapyup-0.8.0.dist-info/METADATA
ultrapyup-0.8.0.dist-info/RECORD
