Metadata-Version: 2.3
Name: ultrapyup
Version: 0.8.0
Summary: A tool to empower your Python projects
Author: teyik0
Author-email: teyik0 <teyik0.fr@icloud.com>
Requires-Dist: inquirerpy>=0.3.4
Requires-Dist: toml>=0.10.2
Requires-Dist: typer>=0.16.0
Requires-Python: >=3.10
Project-URL: Homepage, https://github.com/teyik0/ultrapyup
Project-URL: Repository, https://github.com/teyik0/ultrapyup
